odoo/addons/queue_job_context/README.rst
odoo/addons/queue_job_context/__init__.py
odoo/addons/queue_job_context/__manifest__.py
odoo/addons/queue_job_context/i18n/queue_job_context.pot
odoo/addons/queue_job_context/models/__init__.py
odoo/addons/queue_job_context/models/base.py
odoo/addons/queue_job_context/readme/CONFIGURE.rst
odoo/addons/queue_job_context/readme/CONTRIBUTORS.rst
odoo/addons/queue_job_context/readme/DESCRIPTION.rst
odoo/addons/queue_job_context/static/description/icon.png
odoo/addons/queue_job_context/static/description/index.html
odoo14_addon_queue_job_context-14.0.1.0.1.dist-info/METADATA
odoo14_addon_queue_job_context-14.0.1.0.1.dist-info/WHEEL
odoo14_addon_queue_job_context-14.0.1.0.1.dist-info/top_level.txt
odoo14_addon_queue_job_context-14.0.1.0.1.dist-info/RECORD
